excelchart/__init__.py
excelchart/excelchart.py
excelchart/__pycache__/__init__.cpython-36.pyc
excelchart/__pycache__/excelchart.cpython-36.pyc
excelchart/data/bar.xlsx
excelchart/data/bar2.xlsx
excelchart/data/line.xlsx
excelchart/data/pie.xlsx
excelchart/data/radar.xlsx
excelchart/data/scatter.xlsx
excelchart/data/stock.xlsx
excelchart-0.1.0.dist-info/DESCRIPTION.rst
excelchart-0.1.0.dist-info/METADATA
excelchart-0.1.0.dist-info/RECORD
excelchart-0.1.0.dist-info/WHEEL
excelchart-0.1.0.dist-info/metadata.json
excelchart-0.1.0.dist-info/top_level.txt
