Metadata-Version: 2.0
Name: excelchart
Version: 0.1.0
Summary: Simply create a excel chart.
Home-page: https://github.com/yangjiada/
Author: Jan Yang
Author-email: yang.jiada@foxmail.com
License: MIT
Download-URL: https://github.com/yangjiada//tarball/2018-02-23
Requires-Dist: XlsxWriter (>=1.0.2)
Requires-Dist: pandas
